src/__init__.py
src/sweep_combined_hate.py
src/sweep_germeval.py
src/sweep_germeval_2021.py
src/sweep_hasoc.py
src/sweep_nationality.py
src/sweep_nationality_bert.py
src/sweep_nationality_sklearn.py
src/sweep_nationality_xlm.py
src/sweep_tagesanzeiger.py
src/train_bert.py
src/dataset/__init__.py
src/dataset/base_dataset.py
src/dataset/germeval_2018_dataset.py
src/dataset/germeval_2021_dataset.py
src/dataset/hasoc_2019_dataset.py
src/dataset/hate_dataset.py
src/dataset/hotel_dataset.py
src/dataset/natio_dataset.py
src/dataset/tagesanzeiger_dataset.py
src/dataset/utils.py
src/embedding/__init__.py
src/embedding/bert_embedder.py
src/metrics/__init__.py
src/metrics/standard_metrics.py
src/models/__init__.py
src/models/fasttext_model.py
src/models/roberta_cnn.py
src/models/utils.py
src/preprocessing/__init__.py
src/preprocessing/preprocessor.py
src/tools/__init__.py
src/tools/create_natio_dataset.py
src/tools/create_prejudice_dataset.py
src/tools/create_sentiment_dataset.py
src/training/__init__.py
src/training/trainer.py
src/utils/__init__.py
src/utils/nlp_augmentation.py
src/utils/utils.py
src/utils/utils_console.py
src/utils/utils_embedding.py
src/utils/utils_tensorflow.py
src/utils/utils_visualize.py
test/__init__.py
test/dataset/test_germeval_2018_dataset.py
test/dataset/test_germeval_2021_dataset.py
test/dataset/test_hasoc_2019_dataset.py
test/dataset/test_hate_dataset.py
test/dataset/test_natio_dataset.py
test/dataset/test_tagesanzeiger_dataset.py
test/metrics/test_standard_metrics.py
test/models/test_fasttext_model.py
test/models/test_model_utils.py
test/models/test_roberta_cnn_model.py
test/preprocessing/test_preprocessor.py
prejudice_bias_hotel_reviews-0.0.1.dist-info/METADATA
prejudice_bias_hotel_reviews-0.0.1.dist-info/WHEEL
prejudice_bias_hotel_reviews-0.0.1.dist-info/top_level.txt
prejudice_bias_hotel_reviews-0.0.1.dist-info/RECORD
