Metadata-Version: 2.1
Name: prejudice-bias-hotel-reviews
Version: 0.0.1
Summary: MSE VM01: Prejudice and Bias in Hotel Reviews
Home-page: https://github.com/FabianGroeger96/
Author: Fabian Groeger
Author-email: fabian.groeger@bluewin.ch
License: UNKNOWN
Platform: UNKNOWN
Classifier: Development Status :: 1 - Planning
Classifier: Intended Audience :: Science/Research
Classifier: License :: OSI Approved :: BSD License
Classifier: Operating System :: POSIX :: Linux
Classifier: Programming Language :: Python :: 3
Classifier: Programming Language :: Python :: 3.6
